kmbit_kernel/__init__.py
kmbit_kernel/cli.py
kmbit_kernel/fs.py
kmbit_kernel/index.py
kmbit_kernel/kernel.py
kmbit_kernel/router.py
kmbit_kernel-0.1.0.dist-info/METADATA
kmbit_kernel-0.1.0.dist-info/WHEEL
kmbit_kernel-0.1.0.dist-info/entry_points.txt
kmbit_kernel-0.1.0.dist-info/RECORD
