Metadata-Version: 2.4
Name: kmbit-kernel
Version: 0.1.0
Summary: The AI Filesystem Kernel - Route queries to agents like a filesystem routes to files
Project-URL: Homepage, https://humotica.com
Project-URL: Repository, https://github.com/jaspertvdm/kmbit-kernel
Project-URL: Documentation, https://humotica.com/docs/kmbit
Author-email: Jasper van de Meent <info@humotica.com>, Root AI <root_ai@humotica.nl>
License: MIT
Keywords: agentic-ai,agents,ai,filesystem,humotica,kernel,llm,multi-agent,orchestration,routing
Classifier: Development Status :: 3 - Alpha
Classifier: Intended Audience :: Developers
Classifier: License :: OSI Approved :: MIT License
Classifier: Operating System :: OS Independent
Classifier: Programming Language :: Python :: 3
Classifier: Programming Language :: Python :: 3.10
Classifier: Programming Language :: Python :: 3.11
Classifier: Programming Language :: Python :: 3.12
Classifier: Programming Language :: Python :: 3.13
Classifier: Topic :: Scientific/Engineering :: Artificial Intelligence
Classifier: Topic :: System :: Operating System Kernels
Requires-Python: >=3.10
Provides-Extra: dev
Requires-Dist: pytest>=7.0; extra == 'dev'
